{"client":"Thunder Client","collectionName":"Palma REST API","dateExported":"2021-11-17T14:52:56.380Z","version":"1.1","folders":[],"requests":[{"containerId":"","sortNum":10000,"headers":[{"name":"Accept","value":"*/*"},{"name":"User-Agent","value":"Thunder Client (https://www.thunderclient.io)"}],"colId":"e5a335cf-329c-482b-804f-ec918a943a65","name":"Palma REST - rolelist","url":"http://localhost:8080/api/auth/rolelist?user_type_id=4","method":"GET","modified":"2021-11-17T06:56:57.038Z","created":"2021-11-11T04:55:53.861Z","_id":"0be86ea5-f7d9-42a3-abab-9452afd927a2","params":[{"name":"user_type_id","value":"4","isPath":false}],"tests":[]},{"containerId":"","sortNum":15000,"headers":[{"name":"Accept","value":"*/*"},{"name":"User-Agent","value":"Thunder Client (https://www.thunderclient.io)"}],"colId":"e5a335cf-329c-482b-804f-ec918a943a65","name":"Palma REST - user list","url":"http://localhost:8080/api/user/list?user_type_id=4","method":"GET","modified":"2021-11-17T11:07:28.073Z","created":"2021-11-13T03:19:47.418Z","_id":"b25a63a7-0334-4ea1-a534-43ec04795b53","params":[{"name":"user_type_id","value":"4","isPath":false}],"tests":[]},{"containerId":"","sortNum":16250,"headers":[{"name":"Accept","value":"*/*"},{"name":"User-Agent","value":"Thunder Client (https://www.thunderclient.io)"},{"name":"x-access-token","value":"eyJhbGciOiJIUzI1NiIsInR5cCI6IkpXVCJ9.eyJpZCI6MTQsImlhdCI6MTYzNzEzNjQ2NiwiZXhwIjoxNjM3MjIyODY2fQ.9RjNvtwCx6G9qcAdaxQQQgHoNEjawx1r7vu0NKlu8v0"}],"colId":"e5a335cf-329c-482b-804f-ec918a943a65","name":"Palma REST - user find","url":"http://localhost:8080/api/user/find?email=aaa@test.com","method":"GET","modified":"2021-11-17T10:20:26.409Z","created":"2021-11-17T09:43:46.761Z","_id":"aa827a3e-44f2-4780-b5f2-59a7e2381716","params":[{"name":"email","value":"aaa@test.com","isPath":false}],"body":{"type":"json","raw":"{\"email\":\"test3@test.com\"}","form":[]},"tests":[]},{"containerId":"","sortNum":17500,"headers":[{"name":"Accept","value":"*/*"},{"name":"User-Agent","value":"Thunder Client (https://www.thunderclient.io)"},{"name":"x-access-token","value":"eyJhbGciOiJIUzI1NiIsInR5cCI6IkpXVCJ9.eyJpZCI6MTQsImlhdCI6MTYzNzEzNjQ2NiwiZXhwIjoxNjM3MjIyODY2fQ.9RjNvtwCx6G9qcAdaxQQQgHoNEjawx1r7vu0NKlu8v0"}],"colId":"e5a335cf-329c-482b-804f-ec918a943a65","name":"Palma REST - user detail","url":"http://localhost:8080/api/user/detail","method":"GET","modified":"2021-11-17T08:08:07.558Z","created":"2021-11-13T03:41:15.694Z","_id":"8373592e-d89b-41f0-9bcd-1b0a00b475b9","params":[],"body":{"type":"json","raw":"{\"uid\":\"test3@test.com\"}","form":[]},"tests":[]},{"containerId":"","sortNum":18125,"headers":[{"name":"Accept","value":"*/*"},{"name":"User-Agent","value":"Thunder Client (https://www.thunderclient.io)"},{"name":"x-access-token","value":"eyJhbGciOiJIUzI1NiIsInR5cCI6IkpXVCJ9.eyJpZCI6MTQsImlhdCI6MTYzNzEzNjQ2NiwiZXhwIjoxNjM3MjIyODY2fQ.9RjNvtwCx6G9qcAdaxQQQgHoNEjawx1r7vu0NKlu8v0"}],"colId":"e5a335cf-329c-482b-804f-ec918a943a65","name":"Palma REST - user check page access","url":"http://localhost:8080/api/user/checkpageaccess","method":"POST","modified":"2021-11-17T12:47:51.738Z","created":"2021-11-17T12:16:36.260Z","_id":"8d8fb912-ca7d-4151-a0ff-fc1011ca6674","params":[],"body":{"type":"json","raw":"{\"role\":\"ManufacturerUser\"}","form":[]},"tests":[]},{"containerId":"","sortNum":18750,"headers":[{"name":"Accept","value":"*/*"},{"name":"User-Agent","value":"Thunder Client (https://www.thunderclient.io)"},{"name":"x-access-token","value":"eyJhbGciOiJIUzI1NiIsInR5cCI6IkpXVCJ9.eyJpZCI6MTQsImlhdCI6MTYzNzE1OTkzNiwiZXhwIjoxNjM3MjQ2MzM2fQ.zkJgXycIJzIakPNcdjmiki9yTfDINtbJS9Us9-onhOE"}],"colId":"e5a335cf-329c-482b-804f-ec918a943a65","name":"Palma REST - user update","url":"http://localhost:8080/api/user/update","method":"POST","modified":"2021-11-17T14:39:22.379Z","created":"2021-11-13T12:43:00.692Z","_id":"bd61eb0f-adef-4e3e-b366-f783e0462ace","params":[],"body":{"type":"json","raw":"{\"email\":\"999@test.com\", \"mobile\":99788873,\"status\":1, \"user_type_id\":4, \"roles\":[\"ManufacturerWindowQuote\",\"ManufacturerReports\"]}","form":[]},"tests":[]},{"containerId":"","sortNum":19375,"headers":[{"name":"Accept","value":"*/*"},{"name":"User-Agent","value":"Thunder Client (https://www.thunderclient.io)"},{"name":"x-access-token","value":"eyJhbGciOiJIUzI1NiIsInR5cCI6IkpXVCJ9.eyJpZCI6MTYsImlhdCI6MTYzNzE2MDA2NSwiZXhwIjoxNjM3MjQ2NDY1fQ.xbAP4GyKREpaYuTJVE4DmgXJs6VQq_RDmWxHV-aiXTg"}],"colId":"e5a335cf-329c-482b-804f-ec918a943a65","name":"Palma REST - user modify by other user","url":"http://localhost:8080/api/user/modify","method":"POST","modified":"2021-11-17T14:51:28.663Z","created":"2021-11-17T14:33:30.989Z","_id":"0ea44c50-0c63-405b-b8c6-eda5e3b4c61a","params":[],"body":{"type":"json","raw":"{\"kemail\":\"33@test.com\",\"email\":\"11@test.com\", \"mobile\":99788871,\"status\":1, \"user_type_id\":4, \"roles\":[\"ManufacturerUser\",\"ManufacturerReports\"]}","form":[]},"tests":[]},{"containerId":"","sortNum":20000,"headers":[{"name":"Accept","value":"*/*"},{"name":"User-Agent","value":"Thunder Client (https://www.thunderclient.io)"}],"colId":"e5a335cf-329c-482b-804f-ec918a943a65","name":"Palma REST  - signup","url":"http://localhost:8080/api/auth/signup","method":"POST","modified":"2021-11-17T08:09:10.585Z","created":"2021-11-11T04:55:53.861Z","_id":"75897fc0-9d04-4a58-b056-4a06e8d6f02f","params":[],"body":{"type":"json","raw":"{\"username\":\"test4\",\"email\":\"test4@test.com\",\"password\":\"123456\",\"user_type_id\":\"4\", \"roles\":[\"ManufacturerUser\",\"ManufacturerReports\"]}","form":[]},"tests":[]},{"containerId":"","sortNum":30000,"headers":[{"name":"Accept","value":"*/*"},{"name":"User-Agent","value":"Thunder Client (https://www.thunderclient.io)"}],"colId":"e5a335cf-329c-482b-804f-ec918a943a65","name":"Palma REST  - signin","url":"http://localhost:8080/api/auth/signin","method":"POST","modified":"2021-11-17T14:41:04.960Z","created":"2021-11-13T05:57:24.251Z","_id":"961982ea-f572-4fe1-b4fd-34b0eaf9a3bc","params":[],"body":{"type":"json","raw":"{\"username\":\"test4\",\"password\":\"123456\"}","form":[]},"tests":[]}]}
